{
  "type": "File",
  "start": 0,
  "end": 445,
  "loc": {
    "start": {
      "line": 1,
      "column": 0
    },
    "end": {
      "line": 14,
      "column": 0
    }
  },
  "program": {
    "type": "Program",
    "start": 0,
    "end": 445,
    "loc": {
      "start": {
        "line": 1,
        "column": 0
      },
      "end": {
        "line": 14,
        "column": 0
      }
    },
    "sourceType": "module",
    "body": [
      {
        "type": "ImportDeclaration",
        "start": 0,
        "end": 30,
        "loc": {
          "start": {
            "line": 1,
            "column": 0
          },
          "end": {
            "line": 1,
            "column": 30
          }
        },
        "specifiers": [
          {
            "type": "ImportDefaultSpecifier",
            "start": 7,
            "end": 11,
            "loc": {
              "start": {
                "line": 1,
                "column": 7
              },
              "end": {
                "line": 1,
                "column": 11
              }
            },
            "local": {
              "type": "Identifier",
              "start": 7,
              "end": 11,
              "loc": {
                "start": {
                  "line": 1,
                  "column": 7
                },
                "end": {
                  "line": 1,
                  "column": 11
                },
                "identifierName": "Base"
              },
              "name": "Base"
            }
          }
        ],
        "source": {
          "type": "StringLiteral",
          "start": 17,
          "end": 30,
          "loc": {
            "start": {
              "line": 1,
              "column": 17
            },
            "end": {
              "line": 1,
              "column": 30
            }
          },
          "extra": {
            "rawValue": "./dbBase.js",
            "raw": "'./dbBase.js'"
          },
          "value": "./dbBase.js"
        }
      },
      {
        "type": "ExportDefaultDeclaration",
        "start": 34,
        "end": 443,
        "loc": {
          "start": {
            "line": 3,
            "column": 0
          },
          "end": {
            "line": 13,
            "column": 1
          }
        },
        "declaration": {
          "type": "ClassDeclaration",
          "start": 49,
          "end": 443,
          "loc": {
            "start": {
              "line": 3,
              "column": 15
            },
            "end": {
              "line": 13,
              "column": 1
            }
          },
          "id": {
            "type": "Identifier",
            "start": 55,
            "end": 67,
            "loc": {
              "start": {
                "line": 3,
                "column": 21
              },
              "end": {
                "line": 3,
                "column": 33
              },
              "identifierName": "LoginMethods"
            },
            "name": "LoginMethods"
          },
          "superClass": {
            "type": "Identifier",
            "start": 76,
            "end": 80,
            "loc": {
              "start": {
                "line": 3,
                "column": 42
              },
              "end": {
                "line": 3,
                "column": 46
              },
              "identifierName": "Base"
            },
            "name": "Base"
          },
          "body": {
            "type": "ClassBody",
            "start": 81,
            "end": 443,
            "loc": {
              "start": {
                "line": 3,
                "column": 47
              },
              "end": {
                "line": 13,
                "column": 1
              }
            },
            "body": [
              {
                "type": "ClassProperty",
                "start": 86,
                "end": 263,
                "loc": {
                  "start": {
                    "line": 4,
                    "column": 2
                  },
                  "end": {
                    "line": 8,
                    "column": 3
                  }
                },
                "static": false,
                "computed": false,
                "key": {
                  "type": "Identifier",
                  "start": 86,
                  "end": 93,
                  "loc": {
                    "start": {
                      "line": 4,
                      "column": 2
                    },
                    "end": {
                      "line": 4,
                      "column": 9
                    },
                    "identifierName": "getUser"
                  },
                  "name": "getUser"
                },
                "value": {
                  "type": "ArrowFunctionExpression",
                  "start": 96,
                  "end": 263,
                  "loc": {
                    "start": {
                      "line": 4,
                      "column": 12
                    },
                    "end": {
                      "line": 8,
                      "column": 3
                    }
                  },
                  "id": null,
                  "generator": false,
                  "expression": false,
                  "async": true,
                  "params": [
                    {
                      "type": "Identifier",
                      "start": 103,
                      "end": 111,
                      "loc": {
                        "start": {
                          "line": 4,
                          "column": 19
                        },
                        "end": {
                          "line": 4,
                          "column": 27
                        },
                        "identifierName": "username"
                      },
                      "name": "username"
                    }
                  ],
                  "body": {
                    "type": "BlockStatement",
                    "start": 116,
                    "end": 263,
                    "loc": {
                      "start": {
                        "line": 4,
                        "column": 32
                      },
                      "end": {
                        "line": 8,
                        "column": 3
                      }
                    },
                    "body": [
                      {
                        "type": "VariableDeclaration",
                        "start": 123,
                        "end": 209,
                        "loc": {
                          "start": {
                            "line": 5,
                            "column": 4
                          },
                          "end": {
                            "line": 5,
                            "column": 90
                          }
                        },
                        "declarations": [
                          {
                            "type": "VariableDeclarator",
                            "start": 129,
                            "end": 209,
                            "loc": {
                              "start": {
                                "line": 5,
                                "column": 10
                              },
                              "end": {
                                "line": 5,
                                "column": 90
                              }
                            },
                            "id": {
                              "type": "Identifier",
                              "start": 129,
                              "end": 133,
                              "loc": {
                                "start": {
                                  "line": 5,
                                  "column": 10
                                },
                                "end": {
                                  "line": 5,
                                  "column": 14
                                },
                                "identifierName": "user"
                              },
                              "name": "user"
                            },
                            "init": {
                              "type": "AwaitExpression",
                              "start": 136,
                              "end": 209,
                              "loc": {
                                "start": {
                                  "line": 5,
                                  "column": 17
                                },
                                "end": {
                                  "line": 5,
                                  "column": 90
                                }
                              },
                              "argument": {
                                "type": "CallExpression",
                                "start": 142,
                                "end": 209,
                                "loc": {
                                  "start": {
                                    "line": 5,
                                    "column": 23
                                  },
                                  "end": {
                                    "line": 5,
                                    "column": 90
                                  }
                                },
                                "callee": {
                                  "type": "MemberExpression",
                                  "start": 142,
                                  "end": 155,
                                  "loc": {
                                    "start": {
                                      "line": 5,
                                      "column": 23
                                    },
                                    "end": {
                                      "line": 5,
                                      "column": 36
                                    }
                                  },
                                  "object": {
                                    "type": "ThisExpression",
                                    "start": 142,
                                    "end": 146,
                                    "loc": {
                                      "start": {
                                        "line": 5,
                                        "column": 23
                                      },
                                      "end": {
                                        "line": 5,
                                        "column": 27
                                      }
                                    }
                                  },
                                  "property": {
                                    "type": "Identifier",
                                    "start": 147,
                                    "end": 155,
                                    "loc": {
                                      "start": {
                                        "line": 5,
                                        "column": 28
                                      },
                                      "end": {
                                        "line": 5,
                                        "column": 36
                                      },
                                      "identifierName": "runQuery"
                                    },
                                    "name": "runQuery"
                                  },
                                  "computed": false
                                },
                                "arguments": [
                                  {
                                    "type": "TemplateLiteral",
                                    "start": 156,
                                    "end": 208,
                                    "loc": {
                                      "start": {
                                        "line": 5,
                                        "column": 37
                                      },
                                      "end": {
                                        "line": 5,
                                        "column": 89
                                      }
                                    },
                                    "expressions": [
                                      {
                                        "type": "Identifier",
                                        "start": 197,
                                        "end": 205,
                                        "loc": {
                                          "start": {
                                            "line": 5,
                                            "column": 78
                                          },
                                          "end": {
                                            "line": 5,
                                            "column": 86
                                          },
                                          "identifierName": "username"
                                        },
                                        "name": "username"
                                      }
                                    ],
                                    "quasis": [
                                      {
                                        "type": "TemplateElement",
                                        "start": 157,
                                        "end": 195,
                                        "loc": {
                                          "start": {
                                            "line": 5,
                                            "column": 38
                                          },
                                          "end": {
                                            "line": 5,
                                            "column": 76
                                          }
                                        },
                                        "value": {
                                          "raw": "SELECT * FROM users WHERE username = '",
                                          "cooked": "SELECT * FROM users WHERE username = '"
                                        },
                                        "tail": false
                                      },
                                      {
                                        "type": "TemplateElement",
                                        "start": 206,
                                        "end": 207,
                                        "loc": {
                                          "start": {
                                            "line": 5,
                                            "column": 87
                                          },
                                          "end": {
                                            "line": 5,
                                            "column": 88
                                          }
                                        },
                                        "value": {
                                          "raw": "'",
                                          "cooked": "'"
                                        },
                                        "tail": true
                                      }
                                    ]
                                  }
                                ]
                              }
                            }
                          }
                        ],
                        "kind": "const"
                      },
                      {
                        "type": "ExpressionStatement",
                        "start": 215,
                        "end": 241,
                        "loc": {
                          "start": {
                            "line": 6,
                            "column": 4
                          },
                          "end": {
                            "line": 6,
                            "column": 30
                          }
                        },
                        "expression": {
                          "type": "CallExpression",
                          "start": 215,
                          "end": 241,
                          "loc": {
                            "start": {
                              "line": 6,
                              "column": 4
                            },
                            "end": {
                              "line": 6,
                              "column": 30
                            }
                          },
                          "callee": {
                            "type": "MemberExpression",
                            "start": 215,
                            "end": 226,
                            "loc": {
                              "start": {
                                "line": 6,
                                "column": 4
                              },
                              "end": {
                                "line": 6,
                                "column": 15
                              }
                            },
                            "object": {
                              "type": "Identifier",
                              "start": 215,
                              "end": 222,
                              "loc": {
                                "start": {
                                  "line": 6,
                                  "column": 4
                                },
                                "end": {
                                  "line": 6,
                                  "column": 11
                                },
                                "identifierName": "console"
                              },
                              "name": "console"
                            },
                            "property": {
                              "type": "Identifier",
                              "start": 223,
                              "end": 226,
                              "loc": {
                                "start": {
                                  "line": 6,
                                  "column": 12
                                },
                                "end": {
                                  "line": 6,
                                  "column": 15
                                },
                                "identifierName": "log"
                              },
                              "name": "log"
                            },
                            "computed": false
                          },
                          "arguments": [
                            {
                              "type": "StringLiteral",
                              "start": 227,
                              "end": 234,
                              "loc": {
                                "start": {
                                  "line": 6,
                                  "column": 16
                                },
                                "end": {
                                  "line": 6,
                                  "column": 23
                                }
                              },
                              "extra": {
                                "rawValue": "user:",
                                "raw": "'user:'"
                              },
                              "value": "user:"
                            },
                            {
                              "type": "Identifier",
                              "start": 236,
                              "end": 240,
                              "loc": {
                                "start": {
                                  "line": 6,
                                  "column": 25
                                },
                                "end": {
                                  "line": 6,
                                  "column": 29
                                },
                                "identifierName": "user"
                              },
                              "name": "user"
                            }
                          ]
                        }
                      },
                      {
                        "type": "ReturnStatement",
                        "start": 247,
                        "end": 258,
                        "loc": {
                          "start": {
                            "line": 7,
                            "column": 4
                          },
                          "end": {
                            "line": 7,
                            "column": 15
                          }
                        },
                        "argument": {
                          "type": "Identifier",
                          "start": 254,
                          "end": 258,
                          "loc": {
                            "start": {
                              "line": 7,
                              "column": 11
                            },
                            "end": {
                              "line": 7,
                              "column": 15
                            },
                            "identifierName": "user"
                          },
                          "name": "user"
                        }
                      }
                    ],
                    "directives": []
                  }
                }
              },
              {
                "type": "ClassProperty",
                "start": 269,
                "end": 440,
                "loc": {
                  "start": {
                    "line": 10,
                    "column": 2
                  },
                  "end": {
                    "line": 12,
                    "column": 3
                  }
                },
                "static": false,
                "computed": false,
                "key": {
                  "type": "Identifier",
                  "start": 269,
                  "end": 279,
                  "loc": {
                    "start": {
                      "line": 10,
                      "column": 2
                    },
                    "end": {
                      "line": 10,
                      "column": 12
                    },
                    "identifierName": "createUser"
                  },
                  "name": "createUser"
                },
                "value": {
                  "type": "ArrowFunctionExpression",
                  "start": 282,
                  "end": 440,
                  "loc": {
                    "start": {
                      "line": 10,
                      "column": 15
                    },
                    "end": {
                      "line": 12,
                      "column": 3
                    }
                  },
                  "id": null,
                  "generator": false,
                  "expression": false,
                  "async": true,
                  "params": [
                    {
                      "type": "Identifier",
                      "start": 289,
                      "end": 297,
                      "loc": {
                        "start": {
                          "line": 10,
                          "column": 22
                        },
                        "end": {
                          "line": 10,
                          "column": 30
                        },
                        "identifierName": "username"
                      },
                      "name": "username"
                    },
                    {
                      "type": "Identifier",
                      "start": 299,
                      "end": 307,
                      "loc": {
                        "start": {
                          "line": 10,
                          "column": 32
                        },
                        "end": {
                          "line": 10,
                          "column": 40
                        },
                        "identifierName": "password"
                      },
                      "name": "password"
                    }
                  ],
                  "body": {
                    "type": "BlockStatement",
                    "start": 312,
                    "end": 440,
                    "loc": {
                      "start": {
                        "line": 10,
                        "column": 45
                      },
                      "end": {
                        "line": 12,
                        "column": 3
                      }
                    },
                    "body": [
                      {
                        "type": "ExpressionStatement",
                        "start": 319,
                        "end": 435,
                        "loc": {
                          "start": {
                            "line": 11,
                            "column": 4
                          },
                          "end": {
                            "line": 11,
                            "column": 120
                          }
                        },
                        "expression": {
                          "type": "AwaitExpression",
                          "start": 319,
                          "end": 435,
                          "loc": {
                            "start": {
                              "line": 11,
                              "column": 4
                            },
                            "end": {
                              "line": 11,
                              "column": 120
                            }
                          },
                          "argument": {
                            "type": "CallExpression",
                            "start": 325,
                            "end": 435,
                            "loc": {
                              "start": {
                                "line": 11,
                                "column": 10
                              },
                              "end": {
                                "line": 11,
                                "column": 120
                              }
                            },
                            "callee": {
                              "type": "MemberExpression",
                              "start": 325,
                              "end": 338,
                              "loc": {
                                "start": {
                                  "line": 11,
                                  "column": 10
                                },
                                "end": {
                                  "line": 11,
                                  "column": 23
                                }
                              },
                              "object": {
                                "type": "ThisExpression",
                                "start": 325,
                                "end": 329,
                                "loc": {
                                  "start": {
                                    "line": 11,
                                    "column": 10
                                  },
                                  "end": {
                                    "line": 11,
                                    "column": 14
                                  }
                                }
                              },
                              "property": {
                                "type": "Identifier",
                                "start": 330,
                                "end": 338,
                                "loc": {
                                  "start": {
                                    "line": 11,
                                    "column": 15
                                  },
                                  "end": {
                                    "line": 11,
                                    "column": 23
                                  },
                                  "identifierName": "runQuery"
                                },
                                "name": "runQuery"
                              },
                              "computed": false
                            },
                            "arguments": [
                              {
                                "type": "TemplateLiteral",
                                "start": 339,
                                "end": 434,
                                "loc": {
                                  "start": {
                                    "line": 11,
                                    "column": 24
                                  },
                                  "end": {
                                    "line": 11,
                                    "column": 119
                                  }
                                },
                                "expressions": [
                                  {
                                    "type": "Identifier",
                                    "start": 406,
                                    "end": 414,
                                    "loc": {
                                      "start": {
                                        "line": 11,
                                        "column": 91
                                      },
                                      "end": {
                                        "line": 11,
                                        "column": 99
                                      },
                                      "identifierName": "username"
                                    },
                                    "name": "username"
                                  },
                                  {
                                    "type": "Identifier",
                                    "start": 421,
                                    "end": 429,
                                    "loc": {
                                      "start": {
                                        "line": 11,
                                        "column": 106
                                      },
                                      "end": {
                                        "line": 11,
                                        "column": 114
                                      },
                                      "identifierName": "password"
                                    },
                                    "name": "password"
                                  }
                                ],
                                "quasis": [
                                  {
                                    "type": "TemplateElement",
                                    "start": 340,
                                    "end": 404,
                                    "loc": {
                                      "start": {
                                        "line": 11,
                                        "column": 25
                                      },
                                      "end": {
                                        "line": 11,
                                        "column": 89
                                      }
                                    },
                                    "value": {
                                      "raw": "INSERT INTO users (isactive, username, password) VALUES (true, '",
                                      "cooked": "INSERT INTO users (isactive, username, password) VALUES (true, '"
                                    },
                                    "tail": false
                                  },
                                  {
                                    "type": "TemplateElement",
                                    "start": 415,
                                    "end": 419,
                                    "loc": {
                                      "start": {
                                        "line": 11,
                                        "column": 100
                                      },
                                      "end": {
                                        "line": 11,
                                        "column": 104
                                      }
                                    },
                                    "value": {
                                      "raw": "', '",
                                      "cooked": "', '"
                                    },
                                    "tail": false
                                  },
                                  {
                                    "type": "TemplateElement",
                                    "start": 430,
                                    "end": 433,
                                    "loc": {
                                      "start": {
                                        "line": 11,
                                        "column": 115
                                      },
                                      "end": {
                                        "line": 11,
                                        "column": 118
                                      }
                                    },
                                    "value": {
                                      "raw": "');",
                                      "cooked": "');"
                                    },
                                    "tail": true
                                  }
                                ]
                              }
                            ]
                          }
                        }
                      }
                    ],
                    "directives": []
                  }
                }
              }
            ]
          },
          "leadingComments": [],
          "trailingComments": []
        }
      }
    ],
    "directives": []
  },
  "comments": [],
  "tokens": [
    {
      "type": {
        "label": "import",
        "keyword": "import",
        "beforeExpr": false,
        "startsExpr": true,
        "rightAssociative": false,
        "isLoop": false,
        "isAssign": false,
        "prefix": false,
        "postfix": false,
        "binop": null,
        "updateContext": null
      },
      "value": "import",
      "start": 0,
      "end": 6,
      "loc": {
        "start": {
          "line": 1,
          "column": 0
        },
        "end": {
          "line": 1,
          "column": 6
        }
      }
    },
    {
      "type": {
        "label": "name",
        "beforeExpr": false,
        "startsExpr": true,
        "rightAssociative": false,
        "isLoop": false,
        "isAssign": false,
        "prefix": false,
        "postfix": false,
        "binop": null
      },
      "value": "Base",
      "start": 7,
      "end": 11,
      "loc": {
        "start": {
          "line": 1,
          "column": 7
        },
        "end": {
          "line": 1,
          "column": 11
        }
      }
    },
    {
      "type": {
        "label": "name",
        "beforeExpr": false,
        "startsExpr": true,
        "rightAssociative": false,
        "isLoop": false,
        "isAssign": false,
        "prefix": false,
        "postfix": false,
        "binop": null
      },
      "value": "from",
      "start": 12,
      "end": 16,
      "loc": {
        "start": {
          "line": 1,
          "column": 12
        },
        "end": {
          "line": 1,
          "column": 16
        }
      }
    },
    {
      "type": {
        "label": "string",
        "beforeExpr": false,
        "startsExpr": true,
        "rightAssociative": false,
        "isLoop": false,
        "isAssign": false,
        "prefix": false,
        "postfix": false,
        "binop": null,
        "updateContext": null
      },
      "value": "./dbBase.js",
      "start": 17,
      "end": 30,
      "loc": {
        "start": {
          "line": 1,
          "column": 17
        },
        "end": {
          "line": 1,
          "column": 30
        }
      }
    },
    {
      "type": {
        "label": "export",
        "keyword": "export",
        "beforeExpr": false,
        "startsExpr": false,
        "rightAssociative": false,
        "isLoop": false,
        "isAssign": false,
        "prefix": false,
        "postfix": false,
        "binop": null,
        "updateContext": null
      },
      "value": "export",
      "start": 34,
      "end": 40,
      "loc": {
        "start": {
          "line": 3,
          "column": 0
        },
        "end": {
          "line": 3,
          "column": 6
        }
      }
    },
    {
      "type": {
        "label": "default",
        "keyword": "default",
        "beforeExpr": true,
        "startsExpr": false,
        "rightAssociative": false,
        "isLoop": false,
        "isAssign": false,
        "prefix": false,
        "postfix": false,
        "binop": null,
        "updateContext": null
      },
      "value": "default",
      "start": 41,
      "end": 48,
      "loc": {
        "start": {
          "line": 3,
          "column": 7
        },
        "end": {
          "line": 3,
          "column": 14
        }
      }
    },
    {
      "type": {
        "label": "class",
        "keyword": "class",
        "beforeExpr": false,
        "startsExpr": false,
        "rightAssociative": false,
        "isLoop": false,
        "isAssign": false,
        "prefix": false,
        "postfix": false,
        "binop": null,
        "updateContext": null
      },
      "value": "class",
      "start": 49,
      "end": 54,
      "loc": {
        "start": {
          "line": 3,
          "column": 15
        },
        "end": {
          "line": 3,
          "column": 20
        }
      }
    },
    {
      "type": {
        "label": "name",
        "beforeExpr": false,
        "startsExpr": true,
        "rightAssociative": false,
        "isLoop": false,
        "isAssign": false,
        "prefix": false,
        "postfix": false,
        "binop": null
      },
      "value": "LoginMethods",
      "start": 55,
      "end": 67,
      "loc": {
        "start": {
          "line": 3,
          "column": 21
        },
        "end": {
          "line": 3,
          "column": 33
        }
      }
    },
    {
      "type": {
        "label": "extends",
        "keyword": "extends",
        "beforeExpr": true,
        "startsExpr": false,
        "rightAssociative": false,
        "isLoop": false,
        "isAssign": false,
        "prefix": false,
        "postfix": false,
        "binop": null,
        "updateContext": null
      },
      "value": "extends",
      "start": 68,
      "end": 75,
      "loc": {
        "start": {
          "line": 3,
          "column": 34
        },
        "end": {
          "line": 3,
          "column": 41
        }
      }
    },
    {
      "type": {
        "label": "name",
        "beforeExpr": false,
        "startsExpr": true,
        "rightAssociative": false,
        "isLoop": false,
        "isAssign": false,
        "prefix": false,
        "postfix": false,
        "binop": null
      },
      "value": "Base",
      "start": 76,
      "end": 80,
      "loc": {
        "start": {
          "line": 3,
          "column": 42
        },
        "end": {
          "line": 3,
          "column": 46
        }
      }
    },
    {
      "type": {
        "label": "{",
        "beforeExpr": true,
        "startsExpr": true,
        "rightAssociative": false,
        "isLoop": false,
        "isAssign": false,
        "prefix": false,
        "postfix": false,
        "binop": null
      },
      "start": 81,
      "end": 82,
      "loc": {
        "start": {
          "line": 3,
          "column": 47
        },
        "end": {
          "line": 3,
          "column": 48
        }
      }
    },
    {
      "type": {
        "label": "name",
        "beforeExpr": false,
        "startsExpr": true,
        "rightAssociative": false,
        "isLoop": false,
        "isAssign": false,
        "prefix": false,
        "postfix": false,
        "binop": null
      },
      "value": "getUser",
      "start": 86,
      "end": 93,
      "loc": {
        "start": {
          "line": 4,
          "column": 2
        },
        "end": {
          "line": 4,
          "column": 9
        }
      }
    },
    {
      "type": {
        "label": "=",
        "beforeExpr": true,
        "startsExpr": false,
        "rightAssociative": false,
        "isLoop": false,
        "isAssign": true,
        "prefix": false,
        "postfix": false,
        "binop": null,
        "updateContext": null
      },
      "value": "=",
      "start": 94,
      "end": 95,
      "loc": {
        "start": {
          "line": 4,
          "column": 10
        },
        "end": {
          "line": 4,
          "column": 11
        }
      }
    },
    {
      "type": {
        "label": "name",
        "beforeExpr": false,
        "startsExpr": true,
        "rightAssociative": false,
        "isLoop": false,
        "isAssign": false,
        "prefix": false,
        "postfix": false,
        "binop": null
      },
      "value": "async",
      "start": 96,
      "end": 101,
      "loc": {
        "start": {
          "line": 4,
          "column": 12
        },
        "end": {
          "line": 4,
          "column": 17
        }
      }
    },
    {
      "type": {
        "label": "(",
        "beforeExpr": true,
        "startsExpr": true,
        "rightAssociative": false,
        "isLoop": false,
        "isAssign": false,
        "prefix": false,
        "postfix": false,
        "binop": null
      },
      "start": 102,
      "end": 103,
      "loc": {
        "start": {
          "line": 4,
          "column": 18
        },
        "end": {
          "line": 4,
          "column": 19
        }
      }
    },
    {
      "type": {
        "label": "name",
        "beforeExpr": false,
        "startsExpr": true,
        "rightAssociative": false,
        "isLoop": false,
        "isAssign": false,
        "prefix": false,
        "postfix": false,
        "binop": null
      },
      "value": "username",
      "start": 103,
      "end": 111,
      "loc": {
        "start": {
          "line": 4,
          "column": 19
        },
        "end": {
          "line": 4,
          "column": 27
        }
      }
    },
    {
      "type": {
        "label": ")",
        "beforeExpr": false,
        "startsExpr": false,
        "rightAssociative": false,
        "isLoop": false,
        "isAssign": false,
        "prefix": false,
        "postfix": false,
        "binop": null
      },
      "start": 111,
      "end": 112,
      "loc": {
        "start": {
          "line": 4,
          "column": 27
        },
        "end": {
          "line": 4,
          "column": 28
        }
      }
    },
    {
      "type": {
        "label": "=>",
        "beforeExpr": true,
        "startsExpr": false,
        "rightAssociative": false,
        "isLoop": false,
        "isAssign": false,
        "prefix": false,
        "postfix": false,
        "binop": null,
        "updateContext": null
      },
      "start": 113,
      "end": 115,
      "loc": {
        "start": {
          "line": 4,
          "column": 29
        },
        "end": {
          "line": 4,
          "column": 31
        }
      }
    },
    {
      "type": {
        "label": "{",
        "beforeExpr": true,
        "startsExpr": true,
        "rightAssociative": false,
        "isLoop": false,
        "isAssign": false,
        "prefix": false,
        "postfix": false,
        "binop": null
      },
      "start": 116,
      "end": 117,
      "loc": {
        "start": {
          "line": 4,
          "column": 32
        },
        "end": {
          "line": 4,
          "column": 33
        }
      }
    },
    {
      "type": {
        "label": "const",
        "keyword": "const",
        "beforeExpr": false,
        "startsExpr": false,
        "rightAssociative": false,
        "isLoop": false,
        "isAssign": false,
        "prefix": false,
        "postfix": false,
        "binop": null,
        "updateContext": null
      },
      "value": "const",
      "start": 123,
      "end": 128,
      "loc": {
        "start": {
          "line": 5,
          "column": 4
        },
        "end": {
          "line": 5,
          "column": 9
        }
      }
    },
    {
      "type": {
        "label": "name",
        "beforeExpr": false,
        "startsExpr": true,
        "rightAssociative": false,
        "isLoop": false,
        "isAssign": false,
        "prefix": false,
        "postfix": false,
        "binop": null
      },
      "value": "user",
      "start": 129,
      "end": 133,
      "loc": {
        "start": {
          "line": 5,
          "column": 10
        },
        "end": {
          "line": 5,
          "column": 14
        }
      }
    },
    {
      "type": {
        "label": "=",
        "beforeExpr": true,
        "startsExpr": false,
        "rightAssociative": false,
        "isLoop": false,
        "isAssign": true,
        "prefix": false,
        "postfix": false,
        "binop": null,
        "updateContext": null
      },
      "value": "=",
      "start": 134,
      "end": 135,
      "loc": {
        "start": {
          "line": 5,
          "column": 15
        },
        "end": {
          "line": 5,
          "column": 16
        }
      }
    },
    {
      "type": {
        "label": "name",
        "beforeExpr": false,
        "startsExpr": true,
        "rightAssociative": false,
        "isLoop": false,
        "isAssign": false,
        "prefix": false,
        "postfix": false,
        "binop": null
      },
      "value": "await",
      "start": 136,
      "end": 141,
      "loc": {
        "start": {
          "line": 5,
          "column": 17
        },
        "end": {
          "line": 5,
          "column": 22
        }
      }
    },
    {
      "type": {
        "label": "this",
        "keyword": "this",
        "beforeExpr": false,
        "startsExpr": true,
        "rightAssociative": false,
        "isLoop": false,
        "isAssign": false,
        "prefix": false,
        "postfix": false,
        "binop": null,
        "updateContext": null
      },
      "value": "this",
      "start": 142,
      "end": 146,
      "loc": {
        "start": {
          "line": 5,
          "column": 23
        },
        "end": {
          "line": 5,
          "column": 27
        }
      }
    },
    {
      "type": {
        "label": ".",
        "beforeExpr": false,
        "startsExpr": false,
        "rightAssociative": false,
        "isLoop": false,
        "isAssign": false,
        "prefix": false,
        "postfix": false,
        "binop": null,
        "updateContext": null
      },
      "start": 146,
      "end": 147,
      "loc": {
        "start": {
          "line": 5,
          "column": 27
        },
        "end": {
          "line": 5,
          "column": 28
        }
      }
    },
    {
      "type": {
        "label": "name",
        "beforeExpr": false,
        "startsExpr": true,
        "rightAssociative": false,
        "isLoop": false,
        "isAssign": false,
        "prefix": false,
        "postfix": false,
        "binop": null
      },
      "value": "runQuery",
      "start": 147,
      "end": 155,
      "loc": {
        "start": {
          "line": 5,
          "column": 28
        },
        "end": {
          "line": 5,
          "column": 36
        }
      }
    },
    {
      "type": {
        "label": "(",
        "beforeExpr": true,
        "startsExpr": true,
        "rightAssociative": false,
        "isLoop": false,
        "isAssign": false,
        "prefix": false,
        "postfix": false,
        "binop": null
      },
      "start": 155,
      "end": 156,
      "loc": {
        "start": {
          "line": 5,
          "column": 36
        },
        "end": {
          "line": 5,
          "column": 37
        }
      }
    },
    {
      "type": {
        "label": "`",
        "beforeExpr": false,
        "startsExpr": true,
        "rightAssociative": false,
        "isLoop": false,
        "isAssign": false,
        "prefix": false,
        "postfix": false,
        "binop": null
      },
      "start": 156,
      "end": 157,
      "loc": {
        "start": {
          "line": 5,
          "column": 37
        },
        "end": {
          "line": 5,
          "column": 38
        }
      }
    },
    {
      "type": {
        "label": "template",
        "beforeExpr": false,
        "startsExpr": false,
        "rightAssociative": false,
        "isLoop": false,
        "isAssign": false,
        "prefix": false,
        "postfix": false,
        "binop": null,
        "updateContext": null
      },
      "value": "SELECT * FROM users WHERE username = '",
      "start": 157,
      "end": 195,
      "loc": {
        "start": {
          "line": 5,
          "column": 38
        },
        "end": {
          "line": 5,
          "column": 76
        }
      }
    },
    {
      "type": {
        "label": "${",
        "beforeExpr": true,
        "startsExpr": true,
        "rightAssociative": false,
        "isLoop": false,
        "isAssign": false,
        "prefix": false,
        "postfix": false,
        "binop": null
      },
      "start": 195,
      "end": 197,
      "loc": {
        "start": {
          "line": 5,
          "column": 76
        },
        "end": {
          "line": 5,
          "column": 78
        }
      }
    },
    {
      "type": {
        "label": "name",
        "beforeExpr": false,
        "startsExpr": true,
        "rightAssociative": false,
        "isLoop": false,
        "isAssign": false,
        "prefix": false,
        "postfix": false,
        "binop": null
      },
      "value": "username",
      "start": 197,
      "end": 205,
      "loc": {
        "start": {
          "line": 5,
          "column": 78
        },
        "end": {
          "line": 5,
          "column": 86
        }
      }
    },
    {
      "type": {
        "label": "}",
        "beforeExpr": false,
        "startsExpr": false,
        "rightAssociative": false,
        "isLoop": false,
        "isAssign": false,
        "prefix": false,
        "postfix": false,
        "binop": null
      },
      "start": 205,
      "end": 206,
      "loc": {
        "start": {
          "line": 5,
          "column": 86
        },
        "end": {
          "line": 5,
          "column": 87
        }
      }
    },
    {
      "type": {
        "label": "template",
        "beforeExpr": false,
        "startsExpr": false,
        "rightAssociative": false,
        "isLoop": false,
        "isAssign": false,
        "prefix": false,
        "postfix": false,
        "binop": null,
        "updateContext": null
      },
      "value": "'",
      "start": 206,
      "end": 207,
      "loc": {
        "start": {
          "line": 5,
          "column": 87
        },
        "end": {
          "line": 5,
          "column": 88
        }
      }
    },
    {
      "type": {
        "label": "`",
        "beforeExpr": false,
        "startsExpr": true,
        "rightAssociative": false,
        "isLoop": false,
        "isAssign": false,
        "prefix": false,
        "postfix": false,
        "binop": null
      },
      "start": 207,
      "end": 208,
      "loc": {
        "start": {
          "line": 5,
          "column": 88
        },
        "end": {
          "line": 5,
          "column": 89
        }
      }
    },
    {
      "type": {
        "label": ")",
        "beforeExpr": false,
        "startsExpr": false,
        "rightAssociative": false,
        "isLoop": false,
        "isAssign": false,
        "prefix": false,
        "postfix": false,
        "binop": null
      },
      "start": 208,
      "end": 209,
      "loc": {
        "start": {
          "line": 5,
          "column": 89
        },
        "end": {
          "line": 5,
          "column": 90
        }
      }
    },
    {
      "type": {
        "label": "name",
        "beforeExpr": false,
        "startsExpr": true,
        "rightAssociative": false,
        "isLoop": false,
        "isAssign": false,
        "prefix": false,
        "postfix": false,
        "binop": null
      },
      "value": "console",
      "start": 215,
      "end": 222,
      "loc": {
        "start": {
          "line": 6,
          "column": 4
        },
        "end": {
          "line": 6,
          "column": 11
        }
      }
    },
    {
      "type": {
        "label": ".",
        "beforeExpr": false,
        "startsExpr": false,
        "rightAssociative": false,
        "isLoop": false,
        "isAssign": false,
        "prefix": false,
        "postfix": false,
        "binop": null,
        "updateContext": null
      },
      "start": 222,
      "end": 223,
      "loc": {
        "start": {
          "line": 6,
          "column": 11
        },
        "end": {
          "line": 6,
          "column": 12
        }
      }
    },
    {
      "type": {
        "label": "name",
        "beforeExpr": false,
        "startsExpr": true,
        "rightAssociative": false,
        "isLoop": false,
        "isAssign": false,
        "prefix": false,
        "postfix": false,
        "binop": null
      },
      "value": "log",
      "start": 223,
      "end": 226,
      "loc": {
        "start": {
          "line": 6,
          "column": 12
        },
        "end": {
          "line": 6,
          "column": 15
        }
      }
    },
    {
      "type": {
        "label": "(",
        "beforeExpr": true,
        "startsExpr": true,
        "rightAssociative": false,
        "isLoop": false,
        "isAssign": false,
        "prefix": false,
        "postfix": false,
        "binop": null
      },
      "start": 226,
      "end": 227,
      "loc": {
        "start": {
          "line": 6,
          "column": 15
        },
        "end": {
          "line": 6,
          "column": 16
        }
      }
    },
    {
      "type": {
        "label": "string",
        "beforeExpr": false,
        "startsExpr": true,
        "rightAssociative": false,
        "isLoop": false,
        "isAssign": false,
        "prefix": false,
        "postfix": false,
        "binop": null,
        "updateContext": null
      },
      "value": "user:",
      "start": 227,
      "end": 234,
      "loc": {
        "start": {
          "line": 6,
          "column": 16
        },
        "end": {
          "line": 6,
          "column": 23
        }
      }
    },
    {
      "type": {
        "label": ",",
        "beforeExpr": true,
        "startsExpr": false,
        "rightAssociative": false,
        "isLoop": false,
        "isAssign": false,
        "prefix": false,
        "postfix": false,
        "binop": null,
        "updateContext": null
      },
      "start": 234,
      "end": 235,
      "loc": {
        "start": {
          "line": 6,
          "column": 23
        },
        "end": {
          "line": 6,
          "column": 24
        }
      }
    },
    {
      "type": {
        "label": "name",
        "beforeExpr": false,
        "startsExpr": true,
        "rightAssociative": false,
        "isLoop": false,
        "isAssign": false,
        "prefix": false,
        "postfix": false,
        "binop": null
      },
      "value": "user",
      "start": 236,
      "end": 240,
      "loc": {
        "start": {
          "line": 6,
          "column": 25
        },
        "end": {
          "line": 6,
          "column": 29
        }
      }
    },
    {
      "type": {
        "label": ")",
        "beforeExpr": false,
        "startsExpr": false,
        "rightAssociative": false,
        "isLoop": false,
        "isAssign": false,
        "prefix": false,
        "postfix": false,
        "binop": null
      },
      "start": 240,
      "end": 241,
      "loc": {
        "start": {
          "line": 6,
          "column": 29
        },
        "end": {
          "line": 6,
          "column": 30
        }
      }
    },
    {
      "type": {
        "label": "return",
        "keyword": "return",
        "beforeExpr": true,
        "startsExpr": false,
        "rightAssociative": false,
        "isLoop": false,
        "isAssign": false,
        "prefix": false,
        "postfix": false,
        "binop": null,
        "updateContext": null
      },
      "value": "return",
      "start": 247,
      "end": 253,
      "loc": {
        "start": {
          "line": 7,
          "column": 4
        },
        "end": {
          "line": 7,
          "column": 10
        }
      }
    },
    {
      "type": {
        "label": "name",
        "beforeExpr": false,
        "startsExpr": true,
        "rightAssociative": false,
        "isLoop": false,
        "isAssign": false,
        "prefix": false,
        "postfix": false,
        "binop": null
      },
      "value": "user",
      "start": 254,
      "end": 258,
      "loc": {
        "start": {
          "line": 7,
          "column": 11
        },
        "end": {
          "line": 7,
          "column": 15
        }
      }
    },
    {
      "type": {
        "label": "}",
        "beforeExpr": false,
        "startsExpr": false,
        "rightAssociative": false,
        "isLoop": false,
        "isAssign": false,
        "prefix": false,
        "postfix": false,
        "binop": null
      },
      "start": 262,
      "end": 263,
      "loc": {
        "start": {
          "line": 8,
          "column": 2
        },
        "end": {
          "line": 8,
          "column": 3
        }
      }
    },
    {
      "type": {
        "label": "name",
        "beforeExpr": false,
        "startsExpr": true,
        "rightAssociative": false,
        "isLoop": false,
        "isAssign": false,
        "prefix": false,
        "postfix": false,
        "binop": null
      },
      "value": "createUser",
      "start": 269,
      "end": 279,
      "loc": {
        "start": {
          "line": 10,
          "column": 2
        },
        "end": {
          "line": 10,
          "column": 12
        }
      }
    },
    {
      "type": {
        "label": "=",
        "beforeExpr": true,
        "startsExpr": false,
        "rightAssociative": false,
        "isLoop": false,
        "isAssign": true,
        "prefix": false,
        "postfix": false,
        "binop": null,
        "updateContext": null
      },
      "value": "=",
      "start": 280,
      "end": 281,
      "loc": {
        "start": {
          "line": 10,
          "column": 13
        },
        "end": {
          "line": 10,
          "column": 14
        }
      }
    },
    {
      "type": {
        "label": "name",
        "beforeExpr": false,
        "startsExpr": true,
        "rightAssociative": false,
        "isLoop": false,
        "isAssign": false,
        "prefix": false,
        "postfix": false,
        "binop": null
      },
      "value": "async",
      "start": 282,
      "end": 287,
      "loc": {
        "start": {
          "line": 10,
          "column": 15
        },
        "end": {
          "line": 10,
          "column": 20
        }
      }
    },
    {
      "type": {
        "label": "(",
        "beforeExpr": true,
        "startsExpr": true,
        "rightAssociative": false,
        "isLoop": false,
        "isAssign": false,
        "prefix": false,
        "postfix": false,
        "binop": null
      },
      "start": 288,
      "end": 289,
      "loc": {
        "start": {
          "line": 10,
          "column": 21
        },
        "end": {
          "line": 10,
          "column": 22
        }
      }
    },
    {
      "type": {
        "label": "name",
        "beforeExpr": false,
        "startsExpr": true,
        "rightAssociative": false,
        "isLoop": false,
        "isAssign": false,
        "prefix": false,
        "postfix": false,
        "binop": null
      },
      "value": "username",
      "start": 289,
      "end": 297,
      "loc": {
        "start": {
          "line": 10,
          "column": 22
        },
        "end": {
          "line": 10,
          "column": 30
        }
      }
    },
    {
      "type": {
        "label": ",",
        "beforeExpr": true,
        "startsExpr": false,
        "rightAssociative": false,
        "isLoop": false,
        "isAssign": false,
        "prefix": false,
        "postfix": false,
        "binop": null,
        "updateContext": null
      },
      "start": 297,
      "end": 298,
      "loc": {
        "start": {
          "line": 10,
          "column": 30
        },
        "end": {
          "line": 10,
          "column": 31
        }
      }
    },
    {
      "type": {
        "label": "name",
        "beforeExpr": false,
        "startsExpr": true,
        "rightAssociative": false,
        "isLoop": false,
        "isAssign": false,
        "prefix": false,
        "postfix": false,
        "binop": null
      },
      "value": "password",
      "start": 299,
      "end": 307,
      "loc": {
        "start": {
          "line": 10,
          "column": 32
        },
        "end": {
          "line": 10,
          "column": 40
        }
      }
    },
    {
      "type": {
        "label": ")",
        "beforeExpr": false,
        "startsExpr": false,
        "rightAssociative": false,
        "isLoop": false,
        "isAssign": false,
        "prefix": false,
        "postfix": false,
        "binop": null
      },
      "start": 307,
      "end": 308,
      "loc": {
        "start": {
          "line": 10,
          "column": 40
        },
        "end": {
          "line": 10,
          "column": 41
        }
      }
    },
    {
      "type": {
        "label": "=>",
        "beforeExpr": true,
        "startsExpr": false,
        "rightAssociative": false,
        "isLoop": false,
        "isAssign": false,
        "prefix": false,
        "postfix": false,
        "binop": null,
        "updateContext": null
      },
      "start": 309,
      "end": 311,
      "loc": {
        "start": {
          "line": 10,
          "column": 42
        },
        "end": {
          "line": 10,
          "column": 44
        }
      }
    },
    {
      "type": {
        "label": "{",
        "beforeExpr": true,
        "startsExpr": true,
        "rightAssociative": false,
        "isLoop": false,
        "isAssign": false,
        "prefix": false,
        "postfix": false,
        "binop": null
      },
      "start": 312,
      "end": 313,
      "loc": {
        "start": {
          "line": 10,
          "column": 45
        },
        "end": {
          "line": 10,
          "column": 46
        }
      }
    },
    {
      "type": {
        "label": "name",
        "beforeExpr": false,
        "startsExpr": true,
        "rightAssociative": false,
        "isLoop": false,
        "isAssign": false,
        "prefix": false,
        "postfix": false,
        "binop": null
      },
      "value": "await",
      "start": 319,
      "end": 324,
      "loc": {
        "start": {
          "line": 11,
          "column": 4
        },
        "end": {
          "line": 11,
          "column": 9
        }
      }
    },
    {
      "type": {
        "label": "this",
        "keyword": "this",
        "beforeExpr": false,
        "startsExpr": true,
        "rightAssociative": false,
        "isLoop": false,
        "isAssign": false,
        "prefix": false,
        "postfix": false,
        "binop": null,
        "updateContext": null
      },
      "value": "this",
      "start": 325,
      "end": 329,
      "loc": {
        "start": {
          "line": 11,
          "column": 10
        },
        "end": {
          "line": 11,
          "column": 14
        }
      }
    },
    {
      "type": {
        "label": ".",
        "beforeExpr": false,
        "startsExpr": false,
        "rightAssociative": false,
        "isLoop": false,
        "isAssign": false,
        "prefix": false,
        "postfix": false,
        "binop": null,
        "updateContext": null
      },
      "start": 329,
      "end": 330,
      "loc": {
        "start": {
          "line": 11,
          "column": 14
        },
        "end": {
          "line": 11,
          "column": 15
        }
      }
    },
    {
      "type": {
        "label": "name",
        "beforeExpr": false,
        "startsExpr": true,
        "rightAssociative": false,
        "isLoop": false,
        "isAssign": false,
        "prefix": false,
        "postfix": false,
        "binop": null
      },
      "value": "runQuery",
      "start": 330,
      "end": 338,
      "loc": {
        "start": {
          "line": 11,
          "column": 15
        },
        "end": {
          "line": 11,
          "column": 23
        }
      }
    },
    {
      "type": {
        "label": "(",
        "beforeExpr": true,
        "startsExpr": true,
        "rightAssociative": false,
        "isLoop": false,
        "isAssign": false,
        "prefix": false,
        "postfix": false,
        "binop": null
      },
      "start": 338,
      "end": 339,
      "loc": {
        "start": {
          "line": 11,
          "column": 23
        },
        "end": {
          "line": 11,
          "column": 24
        }
      }
    },
    {
      "type": {
        "label": "`",
        "beforeExpr": false,
        "startsExpr": true,
        "rightAssociative": false,
        "isLoop": false,
        "isAssign": false,
        "prefix": false,
        "postfix": false,
        "binop": null
      },
      "start": 339,
      "end": 340,
      "loc": {
        "start": {
          "line": 11,
          "column": 24
        },
        "end": {
          "line": 11,
          "column": 25
        }
      }
    },
    {
      "type": {
        "label": "template",
        "beforeExpr": false,
        "startsExpr": false,
        "rightAssociative": false,
        "isLoop": false,
        "isAssign": false,
        "prefix": false,
        "postfix": false,
        "binop": null,
        "updateContext": null
      },
      "value": "INSERT INTO users (isactive, username, password) VALUES (true, '",
      "start": 340,
      "end": 404,
      "loc": {
        "start": {
          "line": 11,
          "column": 25
        },
        "end": {
          "line": 11,
          "column": 89
        }
      }
    },
    {
      "type": {
        "label": "${",
        "beforeExpr": true,
        "startsExpr": true,
        "rightAssociative": false,
        "isLoop": false,
        "isAssign": false,
        "prefix": false,
        "postfix": false,
        "binop": null
      },
      "start": 404,
      "end": 406,
      "loc": {
        "start": {
          "line": 11,
          "column": 89
        },
        "end": {
          "line": 11,
          "column": 91
        }
      }
    },
    {
      "type": {
        "label": "name",
        "beforeExpr": false,
        "startsExpr": true,
        "rightAssociative": false,
        "isLoop": false,
        "isAssign": false,
        "prefix": false,
        "postfix": false,
        "binop": null
      },
      "value": "username",
      "start": 406,
      "end": 414,
      "loc": {
        "start": {
          "line": 11,
          "column": 91
        },
        "end": {
          "line": 11,
          "column": 99
        }
      }
    },
    {
      "type": {
        "label": "}",
        "beforeExpr": false,
        "startsExpr": false,
        "rightAssociative": false,
        "isLoop": false,
        "isAssign": false,
        "prefix": false,
        "postfix": false,
        "binop": null
      },
      "start": 414,
      "end": 415,
      "loc": {
        "start": {
          "line": 11,
          "column": 99
        },
        "end": {
          "line": 11,
          "column": 100
        }
      }
    },
    {
      "type": {
        "label": "template",
        "beforeExpr": false,
        "startsExpr": false,
        "rightAssociative": false,
        "isLoop": false,
        "isAssign": false,
        "prefix": false,
        "postfix": false,
        "binop": null,
        "updateContext": null
      },
      "value": "', '",
      "start": 415,
      "end": 419,
      "loc": {
        "start": {
          "line": 11,
          "column": 100
        },
        "end": {
          "line": 11,
          "column": 104
        }
      }
    },
    {
      "type": {
        "label": "${",
        "beforeExpr": true,
        "startsExpr": true,
        "rightAssociative": false,
        "isLoop": false,
        "isAssign": false,
        "prefix": false,
        "postfix": false,
        "binop": null
      },
      "start": 419,
      "end": 421,
      "loc": {
        "start": {
          "line": 11,
          "column": 104
        },
        "end": {
          "line": 11,
          "column": 106
        }
      }
    },
    {
      "type": {
        "label": "name",
        "beforeExpr": false,
        "startsExpr": true,
        "rightAssociative": false,
        "isLoop": false,
        "isAssign": false,
        "prefix": false,
        "postfix": false,
        "binop": null
      },
      "value": "password",
      "start": 421,
      "end": 429,
      "loc": {
        "start": {
          "line": 11,
          "column": 106
        },
        "end": {
          "line": 11,
          "column": 114
        }
      }
    },
    {
      "type": {
        "label": "}",
        "beforeExpr": false,
        "startsExpr": false,
        "rightAssociative": false,
        "isLoop": false,
        "isAssign": false,
        "prefix": false,
        "postfix": false,
        "binop": null
      },
      "start": 429,
      "end": 430,
      "loc": {
        "start": {
          "line": 11,
          "column": 114
        },
        "end": {
          "line": 11,
          "column": 115
        }
      }
    },
    {
      "type": {
        "label": "template",
        "beforeExpr": false,
        "startsExpr": false,
        "rightAssociative": false,
        "isLoop": false,
        "isAssign": false,
        "prefix": false,
        "postfix": false,
        "binop": null,
        "updateContext": null
      },
      "value": "');",
      "start": 430,
      "end": 433,
      "loc": {
        "start": {
          "line": 11,
          "column": 115
        },
        "end": {
          "line": 11,
          "column": 118
        }
      }
    },
    {
      "type": {
        "label": "`",
        "beforeExpr": false,
        "startsExpr": true,
        "rightAssociative": false,
        "isLoop": false,
        "isAssign": false,
        "prefix": false,
        "postfix": false,
        "binop": null
      },
      "start": 433,
      "end": 434,
      "loc": {
        "start": {
          "line": 11,
          "column": 118
        },
        "end": {
          "line": 11,
          "column": 119
        }
      }
    },
    {
      "type": {
        "label": ")",
        "beforeExpr": false,
        "startsExpr": false,
        "rightAssociative": false,
        "isLoop": false,
        "isAssign": false,
        "prefix": false,
        "postfix": false,
        "binop": null
      },
      "start": 434,
      "end": 435,
      "loc": {
        "start": {
          "line": 11,
          "column": 119
        },
        "end": {
          "line": 11,
          "column": 120
        }
      }
    },
    {
      "type": {
        "label": "}",
        "beforeExpr": false,
        "startsExpr": false,
        "rightAssociative": false,
        "isLoop": false,
        "isAssign": false,
        "prefix": false,
        "postfix": false,
        "binop": null
      },
      "start": 439,
      "end": 440,
      "loc": {
        "start": {
          "line": 12,
          "column": 2
        },
        "end": {
          "line": 12,
          "column": 3
        }
      }
    },
    {
      "type": {
        "label": "}",
        "beforeExpr": false,
        "startsExpr": false,
        "rightAssociative": false,
        "isLoop": false,
        "isAssign": false,
        "prefix": false,
        "postfix": false,
        "binop": null
      },
      "start": 442,
      "end": 443,
      "loc": {
        "start": {
          "line": 13,
          "column": 0
        },
        "end": {
          "line": 13,
          "column": 1
        }
      }
    },
    {
      "type": {
        "label": "eof",
        "beforeExpr": false,
        "startsExpr": false,
        "rightAssociative": false,
        "isLoop": false,
        "isAssign": false,
        "prefix": false,
        "postfix": false,
        "binop": null,
        "updateContext": null
      },
      "start": 445,
      "end": 445,
      "loc": {
        "start": {
          "line": 14,
          "column": 0
        },
        "end": {
          "line": 14,
          "column": 0
        }
      }
    }
  ]
}